{"version":2,"created":"2026-07-12","updated":"2026-07-13T04:45:49.529Z","totalSubmissions":6,"uniqueFingerprints":5,"fingerprints":{"aa2bbf12642d380c":{"count":2,"firstSeen":"2026-07-12T20:38:07.582Z","lastSeen":"2026-07-12T20:38:41.015Z","source":"manual","fp":{"detectorVersion":1,"screenClass":"Full HD","engine":"Chrome","botScore":42}},"226b52665808f91a":{"count":1,"firstSeen":"2026-07-12T20:39:42.856Z","lastSeen":"2026-07-12T20:39:42.856Z","source":"manual","fp":{"detectorVersion":1,"screenClass":"Full HD","botScore":48}},"fff188589195192c":{"count":1,"firstSeen":"2026-07-12T20:43:35.387Z","lastSeen":"2026-07-12T20:43:35.387Z","source":"manual","fp":{"detectorVersion":1,"screenClass":"1920x1080","botScore":48}},"aa472f02a678df77":{"count":1,"firstSeen":"2026-07-13T04:45:33.564Z","lastSeen":"2026-07-13T04:45:33.564Z","source":"automation_playwright","fp":{"detectorVersion":1,"screenClass":"Full HD","hasWASM":true,"hasWebGL":true,"hasCanvas":true,"hasAudio":true,"fontCount":7,"gpuClass":"software","tzRegion":"Europe","cpuCores":"high","deviceMemory":"high","darkMode":false,"engine":"V8/Blink (Chrome/Edge)","adblockDetected":false,"totalEntropyBits":null,"botScore":48}},"7de99693782d7ccf":{"count":1,"firstSeen":"2026-07-13T04:45:49.529Z","lastSeen":"2026-07-13T04:45:49.529Z","source":"automation_playwright","fp":{"detectorVersion":1,"screenClass":"HD+","hasWASM":true,"hasWebGL":true,"hasCanvas":true,"hasAudio":true,"fontCount":7,"gpuClass":"software","tzRegion":"Europe","cpuCores":"high","deviceMemory":"high","darkMode":false,"engine":"V8/Blink (Chrome/Edge)","adblockDetected":false,"totalEntropyBits":null,"botScore":48}}},"distributions":{"screenClass":{"Full HD":4,"1920x1080":1,"HD+":1},"engine":{"Chrome":2,"V8/Blink (Chrome/Edge)":2},"source":{"manual":4,"automation_playwright":2},"gpuClass":{"software":2},"tzRegion":{"Europe":2},"cpuCores":{"high":2},"deviceMemory":{"high":2},"fontCount":{"7":2},"hasWASM":{"true":2},"adblockDetected":{"false":2}}}
